IxNetwork/IxNetwork.py
IxNetwork/IxNetworkLegacy.py
IxNetwork/IxNetworkSecure.py
IxNetwork/__init__.py
IxNetwork/requirements.txt
IxNetwork-8.50.1501.9.dist-info/DESCRIPTION.rst
IxNetwork-8.50.1501.9.dist-info/LICENSE.txt
IxNetwork-8.50.1501.9.dist-info/METADATA
IxNetwork-8.50.1501.9.dist-info/RECORD
IxNetwork-8.50.1501.9.dist-info/WHEEL
IxNetwork-8.50.1501.9.dist-info/metadata.json
IxNetwork-8.50.1501.9.dist-info/top_level.txt
IxNetwork-8.50.1501.9.dist-info/zip-safe
