Metadata-Version: 2.0
Name: IxNetwork
Version: 8.50.1501.9
Summary: IxNetwork API Python Bindings
Home-page: https://github.com/ixiacom/ixnetwork-api-py
Author: Ixia
Author-email: diana.galan@keysight.com
License: License :: OSI Approved :: MIT License
Keywords: ixia ixnetwork
Platform: Windows
Platform: Linux
Platform: Solaris
Platform: Mac OS-X
Platform: Unix
Classifier: Development Status :: 5 - Production/Stable
Classifier: License :: OSI Approved :: MIT License
Classifier: Intended Audience :: Information Technology
Classifier: Intended Audience :: System Administrators
Classifier: Intended Audience :: Developers
Classifier: Environment :: No Input/Output (Daemon)
Classifier: Programming Language :: Python :: 2
Classifier: Programming Language :: Python :: 2.7
Classifier: Programming Language :: Python :: 3
Classifier: Programming Language :: Python :: 3.3
Classifier: Programming Language :: Python :: 3.4
Classifier: Programming Language :: Python :: 3.5
Classifier: Programming Language :: Python :: 3.6
Classifier: Topic :: Software Development :: Libraries :: Python Modules
Classifier: Topic :: System :: Distributed Computing
Classifier: Operating System :: Microsoft :: Windows
Classifier: Operating System :: POSIX
Classifier: Operating System :: Unix
Classifier: Operating System :: MacOS
Requires-Dist: backports.ssl (>=0.0.9backports.ssl-match-hostname>=3.5.0.1)
Requires-Dist: pyopenssl (>=17.5.0)
Requires-Dist: requests (>=2.18.4)
Requires-Dist: websocket-client (>=0.47.0)
